{
    "service": "gmail",
    "auth": {
        "user": "ptihomir@gmail.com",
        "pass": "rkwstsilfkzylrkr"
    },
    "defaultFrom": "tihomir@alasdoo.com",
    "defaultTo": "ptihomir@gmail.com",
    "templates": {
        "title": "TEST: DailyReport for {{&date}} {{&hour}}h",
        "body": "Hello,<br/><ul>{{#task}}<li>{{.}}</li>{{/task}}</ul><br/>Regards,<br/>Tihomir Popov"
    },
    "spreadsheetId": "1V2leRjByZS_0t1jlBzsKvTYR8YI0kYkt6QQK2uKg2zU",
    "worksheetId": "od6",
    "worksheetName": "WorkingHours",
    "oauth" : {
        "email": "886016146227-8qqn1g29aeuhj592sstk0msh3jccvb9i@developer.gserviceaccount.com",
        "keyFile": "/alasdoo-key-final.pem"
    }
}
